<?xml version='1.0' encoding='utf-8'?>
<TextureAtlas imagePath="Duet.png">
<SubTexture name="FightIdle0000" x="100" y="123" width="105" height="118" frameX="-18" frameY="-13" frameWidth="140" frameHeight="140" />
<SubTexture name="FightIdle0001" x="100" y="123" width="105" height="118" frameX="-18" frameY="-13" frameWidth="140" frameHeight="140" />
<SubTexture name="FightIdle0002" x="199" y="0" width="105" height="119" frameX="-18" frameY="-12" frameWidth="140" frameHeight="140" />
<SubTexture name="FightIdle0003" x="199" y="0" width="105" height="119" frameX="-18" frameY="-12" frameWidth="140" frameHeight="140" />
<SubTexture name="FightIdle0004" x="199" y="0" width="105" height="119" frameX="-18" frameY="-12" frameWidth="140" frameHeight="140" />
<SubTexture name="FightIdle0005" x="199" y="0" width="105" height="119" frameX="-18" frameY="-12" frameWidth="140" frameHeight="140" />
<SubTexture name="FightIdle0006" x="199" y="0" width="105" height="119" frameX="-18" frameY="-12" frameWidth="140" frameHeight="140" />
<SubTexture name="FightIdle0007" x="199" y="0" width="105" height="119" frameX="-18" frameY="-12" frameWidth="140" frameHeight="140" />
<SubTexture name="FightIdle0008" x="304" y="0" width="104" height="118" frameX="-19" frameY="-13" frameWidth="140" frameHeight="140" />
<SubTexture name="FightIdle0009" x="304" y="0" width="104" height="118" frameX="-19" frameY="-13" frameWidth="140" frameHeight="140" />
<SubTexture name="FightIdle0010" x="408" y="234" width="101" height="116" frameX="-18" frameY="-15" frameWidth="140" frameHeight="140" />
<SubTexture name="FightIdle0011" x="408" y="234" width="101" height="116" frameX="-18" frameY="-15" frameWidth="140" frameHeight="140" />
<SubTexture name="FightIdle0012" x="96" y="242" width="101" height="117" frameX="-18" frameY="-14" frameWidth="140" frameHeight="140" />
<SubTexture name="FightIdle0013" x="96" y="242" width="101" height="117" frameX="-18" frameY="-14" frameWidth="140" frameHeight="140" />
<SubTexture name="FightIdle0014" x="96" y="242" width="101" height="117" frameX="-18" frameY="-14" frameWidth="140" frameHeight="140" />
<SubTexture name="FightIdle0015" x="96" y="242" width="101" height="117" frameX="-18" frameY="-14" frameWidth="140" frameHeight="140" />
<SubTexture name="FightIdle0016" x="96" y="242" width="101" height="117" frameX="-18" frameY="-14" frameWidth="140" frameHeight="140" />
<SubTexture name="FightIdle0017" x="96" y="242" width="101" height="117" frameX="-18" frameY="-14" frameWidth="140" frameHeight="140" />
<SubTexture name="FightIdle0018" x="96" y="242" width="101" height="117" frameX="-18" frameY="-14" frameWidth="140" frameHeight="140" />
<SubTexture name="FightIdle0019" x="96" y="242" width="101" height="117" frameX="-18" frameY="-14" frameWidth="140" frameHeight="140" />
<SubTexture name="MkaDown0000" x="0" y="360" width="93" height="116" frameX="-17" frameY="-15" frameWidth="140" frameHeight="140" />
<SubTexture name="MkaDown0001" x="0" y="360" width="93" height="116" frameX="-17" frameY="-15" frameWidth="140" frameHeight="140" />
<SubTexture name="MkaDown0002" x="0" y="360" width="93" height="116" frameX="-17" frameY="-15" frameWidth="140" frameHeight="140" />
<SubTexture name="MkaDown0003" x="93" y="360" width="94" height="116" frameX="-17" frameY="-15" frameWidth="140" frameHeight="140" />
<SubTexture name="MkaDown0004" x="93" y="360" width="94" height="116" frameX="-17" frameY="-15" frameWidth="140" frameHeight="140" />
<SubTexture name="MkaDown0005" x="93" y="360" width="94" height="116" frameX="-17" frameY="-15" frameWidth="140" frameHeight="140" />
<SubTexture name="MkaDown0006" x="93" y="360" width="94" height="116" frameX="-17" frameY="-15" frameWidth="140" frameHeight="140" />
<SubTexture name="MkaDown0007" x="93" y="360" width="94" height="116" frameX="-17" frameY="-15" frameWidth="140" frameHeight="140" />
<SubTexture name="MkaDown0008" x="93" y="360" width="94" height="116" frameX="-17" frameY="-15" frameWidth="140" frameHeight="140" />
<SubTexture name="MkaDown0009" x="93" y="360" width="94" height="116" frameX="-17" frameY="-15" frameWidth="140" frameHeight="140" />
<SubTexture name="MkaDown0010" x="93" y="360" width="94" height="116" frameX="-17" frameY="-15" frameWidth="140" frameHeight="140" />
<SubTexture name="MkaLeft0000" x="393" y="360" width="97" height="115" frameX="-17" frameY="-15" frameWidth="140" frameHeight="140" />
<SubTexture name="MkaLeft0001" x="393" y="360" width="97" height="115" frameX="-17" frameY="-15" frameWidth="140" frameHeight="140" />
<SubTexture name="MkaLeft0002" x="393" y="360" width="97" height="115" frameX="-17" frameY="-15" frameWidth="140" frameHeight="140" />
<SubTexture name="MkaLeft0003" x="509" y="0" width="99" height="115" frameX="-17" frameY="-15" frameWidth="140" frameHeight="140" />
<SubTexture name="MkaLeft0004" x="509" y="0" width="99" height="115" frameX="-17" frameY="-15" frameWidth="140" frameHeight="140" />
<SubTexture name="MkaLeft0005" x="509" y="0" width="99" height="115" frameX="-17" frameY="-15" frameWidth="140" frameHeight="140" />
<SubTexture name="MkaLeft0006" x="509" y="0" width="99" height="115" frameX="-17" frameY="-15" frameWidth="140" frameHeight="140" />
<SubTexture name="MkaLeft0007" x="509" y="0" width="99" height="115" frameX="-17" frameY="-15" frameWidth="140" frameHeight="140" />
<SubTexture name="MkaLeft0008" x="509" y="0" width="99" height="115" frameX="-17" frameY="-15" frameWidth="140" frameHeight="140" />
<SubTexture name="MkaLeft0009" x="509" y="0" width="99" height="115" frameX="-17" frameY="-15" frameWidth="140" frameHeight="140" />
<SubTexture name="MkaLeft0010" x="509" y="0" width="99" height="115" frameX="-17" frameY="-15" frameWidth="140" frameHeight="140" />
<SubTexture name="MkaRight0000" x="187" y="360" width="104" height="116" frameX="-19" frameY="-15" frameWidth="140" frameHeight="140" />
<SubTexture name="MkaRight0001" x="187" y="360" width="104" height="116" frameX="-19" frameY="-15" frameWidth="140" frameHeight="140" />
<SubTexture name="MkaRight0002" x="291" y="360" width="102" height="116" frameX="-19" frameY="-15" frameWidth="140" frameHeight="140" />
<SubTexture name="MkaRight0003" x="291" y="360" width="102" height="116" frameX="-19" frameY="-15" frameWidth="140" frameHeight="140" />
<SubTexture name="MkaRight0004" x="291" y="360" width="102" height="116" frameX="-19" frameY="-15" frameWidth="140" frameHeight="140" />
<SubTexture name="MkaRight0005" x="291" y="360" width="102" height="116" frameX="-19" frameY="-15" frameWidth="140" frameHeight="140" />
<SubTexture name="MkaRight0006" x="291" y="360" width="102" height="116" frameX="-19" frameY="-15" frameWidth="140" frameHeight="140" />
<SubTexture name="MkaRight0007" x="291" y="360" width="102" height="116" frameX="-19" frameY="-15" frameWidth="140" frameHeight="140" />
<SubTexture name="MkaRight0008" x="291" y="360" width="102" height="116" frameX="-19" frameY="-15" frameWidth="140" frameHeight="140" />
<SubTexture name="MkaRight0009" x="291" y="360" width="102" height="116" frameX="-19" frameY="-15" frameWidth="140" frameHeight="140" />
<SubTexture name="MkaRight0010" x="291" y="360" width="102" height="116" frameX="-19" frameY="-15" frameWidth="140" frameHeight="140" />
<SubTexture name="MkaRight0011" x="291" y="360" width="102" height="116" frameX="-19" frameY="-15" frameWidth="140" frameHeight="140" />
<SubTexture name="MkaRight0012" x="291" y="360" width="102" height="116" frameX="-19" frameY="-15" frameWidth="140" frameHeight="140" />
<SubTexture name="MkaRight0013" x="291" y="360" width="102" height="116" frameX="-19" frameY="-15" frameWidth="140" frameHeight="140" />
<SubTexture name="MkaRight0014" x="291" y="360" width="102" height="116" frameX="-19" frameY="-15" frameWidth="140" frameHeight="140" />
<SubTexture name="MkaUp0000" x="0" y="123" width="100" height="119" frameX="-19" frameY="-12" frameWidth="140" frameHeight="140" />
<SubTexture name="MkaUp0001" x="0" y="123" width="100" height="119" frameX="-19" frameY="-12" frameWidth="140" frameHeight="140" />
<SubTexture name="MkaUp0002" x="0" y="123" width="100" height="119" frameX="-19" frameY="-12" frameWidth="140" frameHeight="140" />
<SubTexture name="MkaUp0003" x="304" y="118" width="98" height="118" frameX="-19" frameY="-13" frameWidth="140" frameHeight="140" />
<SubTexture name="MkaUp0004" x="304" y="118" width="98" height="118" frameX="-19" frameY="-13" frameWidth="140" frameHeight="140" />
<SubTexture name="MkaUp0005" x="304" y="118" width="98" height="118" frameX="-19" frameY="-13" frameWidth="140" frameHeight="140" />
<SubTexture name="MkaUp0006" x="304" y="118" width="98" height="118" frameX="-19" frameY="-13" frameWidth="140" frameHeight="140" />
<SubTexture name="MkaUp0007" x="304" y="118" width="98" height="118" frameX="-19" frameY="-13" frameWidth="140" frameHeight="140" />
<SubTexture name="MkaUp0008" x="304" y="118" width="98" height="118" frameX="-19" frameY="-13" frameWidth="140" frameHeight="140" />
<SubTexture name="MkaUp0009" x="304" y="118" width="98" height="118" frameX="-19" frameY="-13" frameWidth="140" frameHeight="140" />
<SubTexture name="MkaUp0010" x="304" y="118" width="98" height="118" frameX="-19" frameY="-13" frameWidth="140" frameHeight="140" />
<SubTexture name="SenDown0000" x="197" y="242" width="98" height="117" frameX="-22" frameY="-14" frameWidth="140" frameHeight="140" />
<SubTexture name="SenDown0001" x="197" y="242" width="98" height="117" frameX="-22" frameY="-14" frameWidth="140" frameHeight="140" />
<SubTexture name="SenDown0002" x="197" y="242" width="98" height="117" frameX="-22" frameY="-14" frameWidth="140" frameHeight="140" />
<SubTexture name="SenDown0003" x="295" y="242" width="97" height="117" frameX="-23" frameY="-14" frameWidth="140" frameHeight="140" />
<SubTexture name="SenDown0004" x="295" y="242" width="97" height="117" frameX="-23" frameY="-14" frameWidth="140" frameHeight="140" />
<SubTexture name="SenDown0005" x="295" y="242" width="97" height="117" frameX="-23" frameY="-14" frameWidth="140" frameHeight="140" />
<SubTexture name="SenDown0006" x="295" y="242" width="97" height="117" frameX="-23" frameY="-14" frameWidth="140" frameHeight="140" />
<SubTexture name="SenDown0007" x="295" y="242" width="97" height="117" frameX="-23" frameY="-14" frameWidth="140" frameHeight="140" />
<SubTexture name="SenDown0008" x="295" y="242" width="97" height="117" frameX="-23" frameY="-14" frameWidth="140" frameHeight="140" />
<SubTexture name="SenDown0009" x="295" y="242" width="97" height="117" frameX="-23" frameY="-14" frameWidth="140" frameHeight="140" />
<SubTexture name="SenDown0010" x="295" y="242" width="97" height="117" frameX="-23" frameY="-14" frameWidth="140" frameHeight="140" />
<SubTexture name="SenLeft0000" x="408" y="0" width="101" height="117" frameX="-19" frameY="-14" frameWidth="140" frameHeight="140" />
<SubTexture name="SenLeft0001" x="408" y="0" width="101" height="117" frameX="-19" frameY="-14" frameWidth="140" frameHeight="140" />
<SubTexture name="SenLeft0002" x="408" y="0" width="101" height="117" frameX="-19" frameY="-14" frameWidth="140" frameHeight="140" />
<SubTexture name="SenLeft0003" x="408" y="117" width="101" height="117" frameX="-19" frameY="-14" frameWidth="140" frameHeight="140" />
<SubTexture name="SenLeft0004" x="408" y="117" width="101" height="117" frameX="-19" frameY="-14" frameWidth="140" frameHeight="140" />
<SubTexture name="SenLeft0005" x="408" y="117" width="101" height="117" frameX="-19" frameY="-14" frameWidth="140" frameHeight="140" />
<SubTexture name="SenLeft0006" x="408" y="117" width="101" height="117" frameX="-19" frameY="-14" frameWidth="140" frameHeight="140" />
<SubTexture name="SenLeft0007" x="408" y="117" width="101" height="117" frameX="-19" frameY="-14" frameWidth="140" frameHeight="140" />
<SubTexture name="SenLeft0008" x="408" y="117" width="101" height="117" frameX="-19" frameY="-14" frameWidth="140" frameHeight="140" />
<SubTexture name="SenLeft0009" x="408" y="117" width="101" height="117" frameX="-19" frameY="-14" frameWidth="140" frameHeight="140" />
<SubTexture name="SenLeft0010" x="408" y="117" width="101" height="117" frameX="-19" frameY="-14" frameWidth="140" frameHeight="140" />
<SubTexture name="SenRight0000" x="205" y="123" width="95" height="118" frameX="-26" frameY="-13" frameWidth="140" frameHeight="140" />
<SubTexture name="SenRight0001" x="205" y="123" width="95" height="118" frameX="-26" frameY="-13" frameWidth="140" frameHeight="140" />
<SubTexture name="SenRight0002" x="0" y="242" width="96" height="118" frameX="-25" frameY="-13" frameWidth="140" frameHeight="140" />
<SubTexture name="SenRight0003" x="0" y="242" width="96" height="118" frameX="-25" frameY="-13" frameWidth="140" frameHeight="140" />
<SubTexture name="SenRight0004" x="0" y="242" width="96" height="118" frameX="-25" frameY="-13" frameWidth="140" frameHeight="140" />
<SubTexture name="SenRight0005" x="0" y="242" width="96" height="118" frameX="-25" frameY="-13" frameWidth="140" frameHeight="140" />
<SubTexture name="SenRight0006" x="0" y="242" width="96" height="118" frameX="-25" frameY="-13" frameWidth="140" frameHeight="140" />
<SubTexture name="SenRight0007" x="0" y="242" width="96" height="118" frameX="-25" frameY="-13" frameWidth="140" frameHeight="140" />
<SubTexture name="SenRight0008" x="0" y="242" width="96" height="118" frameX="-25" frameY="-13" frameWidth="140" frameHeight="140" />
<SubTexture name="SenRight0009" x="0" y="242" width="96" height="118" frameX="-25" frameY="-13" frameWidth="140" frameHeight="140" />
<SubTexture name="SenRight0010" x="0" y="242" width="96" height="118" frameX="-25" frameY="-13" frameWidth="140" frameHeight="140" />
<SubTexture name="SenRight0011" x="0" y="242" width="96" height="118" frameX="-25" frameY="-13" frameWidth="140" frameHeight="140" />
<SubTexture name="SenRight0012" x="0" y="242" width="96" height="118" frameX="-25" frameY="-13" frameWidth="140" frameHeight="140" />
<SubTexture name="SenRight0013" x="0" y="242" width="96" height="118" frameX="-25" frameY="-13" frameWidth="140" frameHeight="140" />
<SubTexture name="SenRight0014" x="0" y="242" width="96" height="118" frameX="-25" frameY="-13" frameWidth="140" frameHeight="140" />
<SubTexture name="SenUp0000" x="0" y="0" width="99" height="123" frameX="-22" frameY="-8" frameWidth="140" frameHeight="140" />
<SubTexture name="SenUp0001" x="0" y="0" width="99" height="123" frameX="-22" frameY="-8" frameWidth="140" frameHeight="140" />
<SubTexture name="SenUp0002" x="99" y="0" width="100" height="123" frameX="-21" frameY="-8" frameWidth="140" frameHeight="140" />
<SubTexture name="SenUp0003" x="99" y="0" width="100" height="123" frameX="-21" frameY="-8" frameWidth="140" frameHeight="140" />
<SubTexture name="SenUp0004" x="99" y="0" width="100" height="123" frameX="-21" frameY="-8" frameWidth="140" frameHeight="140" />
<SubTexture name="SenUp0005" x="99" y="0" width="100" height="123" frameX="-21" frameY="-8" frameWidth="140" frameHeight="140" />
<SubTexture name="SenUp0006" x="99" y="0" width="100" height="123" frameX="-21" frameY="-8" frameWidth="140" frameHeight="140" />
<SubTexture name="SenUp0007" x="99" y="0" width="100" height="123" frameX="-21" frameY="-8" frameWidth="140" frameHeight="140" />
<SubTexture name="SenUp0008" x="99" y="0" width="100" height="123" frameX="-21" frameY="-8" frameWidth="140" frameHeight="140" />
<SubTexture name="SenUp0009" x="99" y="0" width="100" height="123" frameX="-21" frameY="-8" frameWidth="140" frameHeight="140" />
<SubTexture name="SenUp0010" x="99" y="0" width="100" height="123" frameX="-21" frameY="-8" frameWidth="140" frameHeight="140" />
<SubTexture name="SenUp0011" x="99" y="0" width="100" height="123" frameX="-21" frameY="-8" frameWidth="140" frameHeight="140" />
<SubTexture name="SenUp0012" x="99" y="0" width="100" height="123" frameX="-21" frameY="-8" frameWidth="140" frameHeight="140" />
<SubTexture name="SenUp0013" x="99" y="0" width="100" height="123" frameX="-21" frameY="-8" frameWidth="140" frameHeight="140" />
<SubTexture name="SenUp0014" x="99" y="0" width="100" height="123" frameX="-21" frameY="-8" frameWidth="140" frameHeight="140" />
</TextureAtlas>
